LICENSE
MANIFEST.in
README.md
setup.py
django_gravy.egg-info/PKG-INFO
django_gravy.egg-info/SOURCES.txt
django_gravy.egg-info/dependency_links.txt
django_gravy.egg-info/not-zip-safe
django_gravy.egg-info/requires.txt
django_gravy.egg-info/top_level.txt
gravy/__init__.py
gravy/functional.py
gravy/geo.py
gravy/images.py
gravy/middleware.py
gravy/utils.py
gravy/views.py
gravy/core/__init__.py
gravy/core/files/__init__.py
gravy/core/files/storage.py
gravy/db/__init__.py
gravy/db/models/__init__.py
gravy/db/models/crypto.py
gravy/db/models/fields.py
gravy/db/models/registration.py
gravy/forms/__init__.py
gravy/forms/fields.py
gravy/forms/widgets.py
gravy/forms/theme/__init__.py
gravy/forms/theme/base.py
gravy/forms/theme/bootstrap.py
gravy/lzo/__init__.py
gravy/lzo/_binding.py
gravy/lzo/lzo1x.py
gravy/ogg/__init__.py
gravy/ogg/_binding.py
gravy/sndfile/__init__.py
gravy/sndfile/_binding.py
gravy/sndfile/util.py
gravy/static/css/bootstrap-combobox.css
gravy/static/css/bootstrap-datetimepicker.css
gravy/static/css/bootstrap-treeview.min.css
gravy/static/css/bootstrap.checkboxToggle.css
gravy/static/css/bootstrap.dateRangePicker.css
gravy/static/css/bootstrap.fileInput.css
gravy/static/css/bootstrap.min.css
gravy/static/css/dataTables.bootstrap.min.css
gravy/static/css/jquery.dataTables.css
gravy/static/css/jquery.dataTables.min.css
gravy/static/css/jquery.namedMultiWidget.css
gravy/static/css/jquery.repeatNamedMultiWidget.css
gravy/static/css/jquery.simpleMap.css
gravy/static/css/jquery.term.css
gravy/static/css/loader.css
gravy/static/fonts/glyphicons-halflings-regular.eot
gravy/static/fonts/glyphicons-halflings-regular.svg
gravy/static/fonts/glyphicons-halflings-regular.ttf
gravy/static/fonts/glyphicons-halflings-regular.woff
gravy/static/fonts/glyphicons-halflings-regular.woff2
gravy/static/fonts/stencil.ttf
gravy/static/images/back_disabled.png
gravy/static/images/back_enabled.png
gravy/static/images/back_enabled_hover.png
gravy/static/images/forward_disabled.png
gravy/static/images/forward_enabled.png
gravy/static/images/forward_enabled_hover.png
gravy/static/images/sort_asc.png
gravy/static/images/sort_asc_disabled.png
gravy/static/images/sort_both.png
