Metadata-Version: 1.1
Name: django-gravy
Version: 0.2.0
Summary: Reusable extras for Django (the gravy).
Home-page: https://github.com/greenbender/django-gravy
Author: greenbender
Author-email: byron.platt@gmail.com
License: BSD License
Platform: UNKNOWN
Classifier: Environment :: Web Environment
Classifier: Framework :: Django
Classifier: Intended Audience :: Developers
Classifier: License :: OSI Approved :: BSD License
Classifier: Operating System :: OS Independent
Classifier: Programming Language :: Python
Classifier: Programming Language :: Python :: 2.7
Classifier: Topic :: Internet :: WWW/HTTP
Classifier: Topic :: Internet :: WWW/HTTP :: Dynamic Content
